funlp/TextRank4Sentence.py
funlp/TextRank4Word.py
funlp/__init__.py
funlp/__version__.py
funlp/cli.py
funlp/paths.py
funlp/py.typed
funlp/utils.py
funlp/datasets/stopwords.txt
funlp/datasets/userdict.txt
funlp/datasets/fonts/simhei.ttf
funlp-0.1.5.data/data/LICENSE
funlp-0.1.5.dist-info/LICENSE
funlp-0.1.5.dist-info/METADATA
funlp-0.1.5.dist-info/WHEEL
funlp-0.1.5.dist-info/entry_points.txt
funlp-0.1.5.dist-info/top_level.txt
funlp-0.1.5.dist-info/RECORD
