Metadata-Version: 2.1
Name: funlp
Version: 0.1.5
Summary: Having fun with language processing 🐳
Home-page: https://github.com/szj2ys/funlp
Author: szj
Author-email: szj2ys@qq.com
License: MIT
Platform: UNKNOWN
Classifier: License :: OSI Approved :: MIT License
Classifier: Programming Language :: Python :: 3.7
Classifier: Programming Language :: Python :: 3.8
Classifier: Programming Language :: Python :: Implementation :: PyPy
Requires-Python: >=3.6.0
Requires-Dist: click
Requires-Dist: click-help-colors
Requires-Dist: cython
Requires-Dist: numpy
Requires-Dist: jieba
Requires-Dist: stopwds
Requires-Dist: gensim (>=3.5.0)
